gradio_model3dgs/__init__.py
gradio_model3dgs/model3dgs.py
gradio_model3dgs/model3dgs.pyi
gradio_model3dgs/templates/component/__vite-browser-external-2447137e.js
gradio_model3dgs/templates/component/index.js
gradio_model3dgs/templates/component/style.css
gradio_model3dgs/templates/component/wrapper-98f94c21-f7f71f53.js
gradio_model3dgs/templates/example/index.js
gradio_model3dgs/templates/example/style.css
gradio_model3dgs-0.2.5.dist-info/METADATA
gradio_model3dgs-0.2.5.dist-info/WHEEL
gradio_model3dgs-0.2.5.dist-info/RECORD
